{
  "best_metric": null,
  "best_model_checkpoint": null,
  "epoch": 5.0,
  "eval_steps": 500,
  "global_step": 505,
  "is_hyper_param_search": false,
  "is_local_process_zero": true,
  "is_world_process_zero": true,
  "log_history": [
    {
      "epoch": 1.0,
      "learning_rate": 1.723241854616174e-05,
      "loss": 0.0967,
      "step": 101
    },
    {
      "epoch": 1.0,
      "eval_loss": 0.6051782369613647,
      "eval_macro_f1": 0.7881139486449626,
      "eval_runtime": 1.4749,
      "eval_samples_per_second": 660.399,
      "eval_steps_per_second": 21.019,
      "step": 101
    },
    {
      "epoch": 2.0,
      "learning_rate": 1.2924313909621303e-05,
      "loss": 0.0972,
      "step": 202
    },
    {
      "epoch": 2.0,
      "eval_loss": 0.5729288458824158,
      "eval_macro_f1": 0.7854277012946653,
      "eval_runtime": 1.4784,
      "eval_samples_per_second": 658.829,
      "eval_steps_per_second": 20.969,
      "step": 202
    },
    {
      "epoch": 3.0,
      "learning_rate": 8.61620927308087e-06,
      "loss": 0.0865,
      "step": 303
    },
    {
      "epoch": 3.0,
      "eval_loss": 0.5890918970108032,
      "eval_macro_f1": 0.7856347799623125,
      "eval_runtime": 1.4764,
      "eval_samples_per_second": 659.705,
      "eval_steps_per_second": 20.997,
      "step": 303
    },
    {
      "epoch": 4.0,
      "learning_rate": 4.308104636540435e-06,
      "loss": 0.0683,
      "step": 404
    },
    {
      "epoch": 4.0,
      "eval_loss": 0.5915146470069885,
      "eval_macro_f1": 0.7818220590232701,
      "eval_runtime": 1.4751,
      "eval_samples_per_second": 660.314,
      "eval_steps_per_second": 21.016,
      "step": 404
    },
    {
      "epoch": 5.0,
      "learning_rate": 0.0,
      "loss": 0.0766,
      "step": 505
    },
    {
      "epoch": 5.0,
      "eval_loss": 0.5854744911193848,
      "eval_macro_f1": 0.7861204386584377,
      "eval_runtime": 1.4768,
      "eval_samples_per_second": 659.551,
      "eval_steps_per_second": 20.992,
      "step": 505
    },
    {
      "epoch": 5.0,
      "step": 505,
      "total_flos": 678149212492800.0,
      "train_loss": 0.08506361328729309,
      "train_runtime": 60.4149,
      "train_samples_per_second": 266.408,
      "train_steps_per_second": 8.359
    },
    {
      "epoch": 5.0,
      "eval_loss": 0.5854744911193848,
      "eval_macro_f1": 0.7861204386584377,
      "eval_runtime": 1.4778,
      "eval_samples_per_second": 659.107,
      "eval_steps_per_second": 20.978,
      "step": 505
    }
  ],
  "logging_steps": 500,
  "max_steps": 505,
  "num_input_tokens_seen": 0,
  "num_train_epochs": 5,
  "save_steps": 500,
  "total_flos": 678149212492800.0,
  "train_batch_size": 32,
  "trial_name": null,
  "trial_params": null
}
