{
  "best_metric": null,
  "best_model_checkpoint": null,
  "epoch": 11.0,
  "eval_steps": 500,
  "global_step": 583,
  "is_hyper_param_search": false,
  "is_local_process_zero": true,
  "is_world_process_zero": true,
  "log_history": [
    {
      "epoch": 1.0,
      "learning_rate": 9.363333429704605e-05,
      "loss": 1.4808,
      "step": 53
    },
    {
      "epoch": 1.0,
      "eval_loss": 1.3422983884811401,
      "eval_macro_f1": 0.11368015414258188,
      "eval_runtime": 0.9976,
      "eval_samples_per_second": 114.278,
      "eval_steps_per_second": 4.01,
      "step": 53
    },
    {
      "epoch": 2.0,
      "learning_rate": 8.427000086734145e-05,
      "loss": 1.281,
      "step": 106
    },
    {
      "epoch": 2.0,
      "eval_loss": 1.1544573307037354,
      "eval_macro_f1": 0.19664055080721746,
      "eval_runtime": 1.0406,
      "eval_samples_per_second": 109.547,
      "eval_steps_per_second": 3.844,
      "step": 106
    },
    {
      "epoch": 3.0,
      "learning_rate": 7.490666743763685e-05,
      "loss": 1.1077,
      "step": 159
    },
    {
      "epoch": 3.0,
      "eval_loss": 0.9924285411834717,
      "eval_macro_f1": 0.3137422542944544,
      "eval_runtime": 1.0695,
      "eval_samples_per_second": 106.589,
      "eval_steps_per_second": 3.74,
      "step": 159
    },
    {
      "epoch": 4.0,
      "learning_rate": 6.554333400793224e-05,
      "loss": 1.0014,
      "step": 212
    },
    {
      "epoch": 4.0,
      "eval_loss": 0.8937486410140991,
      "eval_macro_f1": 0.33456412868177576,
      "eval_runtime": 1.0753,
      "eval_samples_per_second": 106.022,
      "eval_steps_per_second": 3.72,
      "step": 212
    },
    {
      "epoch": 5.0,
      "learning_rate": 5.6180000578227625e-05,
      "loss": 0.9111,
      "step": 265
    },
    {
      "epoch": 5.0,
      "eval_loss": 0.8115323781967163,
      "eval_macro_f1": 0.4209610592589316,
      "eval_runtime": 1.0211,
      "eval_samples_per_second": 111.645,
      "eval_steps_per_second": 3.917,
      "step": 265
    },
    {
      "epoch": 6.0,
      "learning_rate": 4.6816667148523024e-05,
      "loss": 0.8667,
      "step": 318
    },
    {
      "epoch": 6.0,
      "eval_loss": 0.9056428074836731,
      "eval_macro_f1": 0.4088791822289746,
      "eval_runtime": 1.0737,
      "eval_samples_per_second": 106.171,
      "eval_steps_per_second": 3.725,
      "step": 318
    },
    {
      "epoch": 7.0,
      "learning_rate": 3.7453333718818423e-05,
      "loss": 0.8213,
      "step": 371
    },
    {
      "epoch": 7.0,
      "eval_loss": 0.797239363193512,
      "eval_macro_f1": 0.4614728364728365,
      "eval_runtime": 1.0969,
      "eval_samples_per_second": 103.927,
      "eval_steps_per_second": 3.647,
      "step": 371
    },
    {
      "epoch": 8.0,
      "learning_rate": 2.8090000289113813e-05,
      "loss": 0.7875,
      "step": 424
    },
    {
      "epoch": 8.0,
      "eval_loss": 0.7163049578666687,
      "eval_macro_f1": 0.4786621217899822,
      "eval_runtime": 1.0725,
      "eval_samples_per_second": 106.292,
      "eval_steps_per_second": 3.73,
      "step": 424
    },
    {
      "epoch": 9.0,
      "learning_rate": 1.8726666859409212e-05,
      "loss": 0.7602,
      "step": 477
    },
    {
      "epoch": 9.0,
      "eval_loss": 0.7278550863265991,
      "eval_macro_f1": 0.4667674709092105,
      "eval_runtime": 1.0718,
      "eval_samples_per_second": 106.366,
      "eval_steps_per_second": 3.732,
      "step": 477
    },
    {
      "epoch": 10.0,
      "learning_rate": 9.363333429704606e-06,
      "loss": 0.7308,
      "step": 530
    },
    {
      "epoch": 10.0,
      "eval_loss": 0.7187297940254211,
      "eval_macro_f1": 0.4756792439719269,
      "eval_runtime": 1.0765,
      "eval_samples_per_second": 105.901,
      "eval_steps_per_second": 3.716,
      "step": 530
    },
    {
      "epoch": 11.0,
      "learning_rate": 0.0,
      "loss": 0.7119,
      "step": 583
    },
    {
      "epoch": 11.0,
      "eval_loss": 0.7084466218948364,
      "eval_macro_f1": 0.4756792439719269,
      "eval_runtime": 1.0826,
      "eval_samples_per_second": 105.297,
      "eval_steps_per_second": 3.695,
      "step": 583
    },
    {
      "epoch": 11.0,
      "step": 583,
      "total_flos": 782340122108160.0,
      "train_loss": 0.9509554318253008,
      "train_runtime": 338.6339,
      "train_samples_per_second": 54.832,
      "train_steps_per_second": 1.722
    },
    {
      "epoch": 11.0,
      "eval_loss": 0.8998730778694153,
      "eval_macro_f1": 0.5123155698737094,
      "eval_runtime": 1.2511,
      "eval_samples_per_second": 111.104,
      "eval_steps_per_second": 3.997,
      "step": 583
    }
  ],
  "logging_steps": 500,
  "max_steps": 583,
  "num_input_tokens_seen": 0,
  "num_train_epochs": 11,
  "save_steps": 500,
  "total_flos": 782340122108160.0,
  "train_batch_size": 32,
  "trial_name": null,
  "trial_params": null
}
