{
  "best_metric": null,
  "best_model_checkpoint": null,
  "epoch": 5.0,
  "eval_steps": 500,
  "global_step": 135,
  "is_hyper_param_search": false,
  "is_local_process_zero": true,
  "is_world_process_zero": true,
  "log_history": [
    {
      "epoch": 1.0,
      "learning_rate": 0.0002722930718631224,
      "loss": 0.0729,
      "step": 27
    },
    {
      "epoch": 1.0,
      "eval_loss": 1.9269262552261353,
      "eval_macro_f1": 0.6465112779125985,
      "eval_runtime": 0.4578,
      "eval_samples_per_second": 303.601,
      "eval_steps_per_second": 6.553,
      "step": 27
    },
    {
      "epoch": 2.0,
      "learning_rate": 0.00020421980389734177,
      "loss": 0.0436,
      "step": 54
    },
    {
      "epoch": 2.0,
      "eval_loss": 1.9435174465179443,
      "eval_macro_f1": 0.6596321514742567,
      "eval_runtime": 0.4544,
      "eval_samples_per_second": 305.867,
      "eval_steps_per_second": 6.601,
      "step": 54
    },
    {
      "epoch": 3.0,
      "learning_rate": 0.0001361465359315612,
      "loss": 0.0358,
      "step": 81
    },
    {
      "epoch": 3.0,
      "eval_loss": 1.9535645246505737,
      "eval_macro_f1": 0.6555529576806173,
      "eval_runtime": 0.2526,
      "eval_samples_per_second": 550.31,
      "eval_steps_per_second": 11.877,
      "step": 81
    },
    {
      "epoch": 4.0,
      "learning_rate": 6.80732679657806e-05,
      "loss": 0.0276,
      "step": 108
    },
    {
      "epoch": 4.0,
      "eval_loss": 1.961826205253601,
      "eval_macro_f1": 0.6577810417096132,
      "eval_runtime": 0.5247,
      "eval_samples_per_second": 264.894,
      "eval_steps_per_second": 5.717,
      "step": 108
    },
    {
      "epoch": 5.0,
      "learning_rate": 0.0,
      "loss": 0.0215,
      "step": 135
    },
    {
      "epoch": 5.0,
      "eval_loss": 1.9536510705947876,
      "eval_macro_f1": 0.6587853416424845,
      "eval_runtime": 0.5006,
      "eval_samples_per_second": 277.642,
      "eval_steps_per_second": 5.992,
      "step": 135
    },
    {
      "epoch": 5.0,
      "step": 135,
      "total_flos": 355609146412800.0,
      "train_loss": 0.040289992756313744,
      "train_runtime": 58.8991,
      "train_samples_per_second": 143.296,
      "train_steps_per_second": 2.292
    },
    {
      "epoch": 5.0,
      "eval_loss": 1.9536510705947876,
      "eval_macro_f1": 0.6587853416424845,
      "eval_runtime": 0.505,
      "eval_samples_per_second": 275.231,
      "eval_steps_per_second": 5.94,
      "step": 135
    }
  ],
  "logging_steps": 500,
  "max_steps": 135,
  "num_input_tokens_seen": 0,
  "num_train_epochs": 5,
  "save_steps": 500,
  "total_flos": 355609146412800.0,
  "train_batch_size": 64,
  "trial_name": null,
  "trial_params": null
}
