{
  "best_metric": 0.9438797235488892,
  "best_model_checkpoint": "./training_output/cs_roberta_base_citation_intent_seq_bn_training_adapter_v01/trial_4/seed_9091/checkpoint-28",
  "epoch": 5.0,
  "eval_steps": 500,
  "global_step": 70,
  "is_hyper_param_search": false,
  "is_local_process_zero": true,
  "is_world_process_zero": true,
  "log_history": [
    {
      "epoch": 1.0,
      "learning_rate": 0.00014847845484838927,
      "loss": 0.1632,
      "step": 14
    },
    {
      "epoch": 1.0,
      "eval_loss": 1.0126358270645142,
      "eval_macro_f1": 0.6680385445395798,
      "eval_runtime": 0.3827,
      "eval_samples_per_second": 363.171,
      "eval_steps_per_second": 5.225,
      "step": 14
    },
    {
      "epoch": 2.0,
      "learning_rate": 0.00011135884113629195,
      "loss": 0.1315,
      "step": 28
    },
    {
      "epoch": 2.0,
      "eval_loss": 0.9438797235488892,
      "eval_macro_f1": 0.7210513991335908,
      "eval_runtime": 0.4407,
      "eval_samples_per_second": 315.404,
      "eval_steps_per_second": 4.538,
      "step": 28
    },
    {
      "epoch": 3.0,
      "learning_rate": 7.423922742419463e-05,
      "loss": 0.1115,
      "step": 42
    },
    {
      "epoch": 3.0,
      "eval_loss": 0.996818482875824,
      "eval_macro_f1": 0.6994674108959823,
      "eval_runtime": 0.4384,
      "eval_samples_per_second": 317.071,
      "eval_steps_per_second": 4.562,
      "step": 42
    },
    {
      "epoch": 4.0,
      "learning_rate": 3.711961371209732e-05,
      "loss": 0.1027,
      "step": 56
    },
    {
      "epoch": 4.0,
      "eval_loss": 1.0057289600372314,
      "eval_macro_f1": 0.6779434210735081,
      "eval_runtime": 0.4222,
      "eval_samples_per_second": 329.196,
      "eval_steps_per_second": 4.737,
      "step": 56
    },
    {
      "epoch": 5.0,
      "learning_rate": 0.0,
      "loss": 0.0845,
      "step": 70
    },
    {
      "epoch": 5.0,
      "eval_loss": 1.0015543699264526,
      "eval_macro_f1": 0.7107533339676197,
      "eval_runtime": 0.4381,
      "eval_samples_per_second": 317.259,
      "eval_steps_per_second": 4.565,
      "step": 70
    },
    {
      "epoch": 5.0,
      "step": 70,
      "total_flos": 355609146412800.0,
      "train_loss": 0.1186646546636309,
      "train_runtime": 52.0691,
      "train_samples_per_second": 162.092,
      "train_steps_per_second": 1.344
    },
    {
      "epoch": 5.0,
      "eval_loss": 0.9438797235488892,
      "eval_macro_f1": 0.7210513991335908,
      "eval_runtime": 0.4219,
      "eval_samples_per_second": 329.479,
      "eval_steps_per_second": 4.741,
      "step": 70
    }
  ],
  "logging_steps": 500,
  "max_steps": 70,
  "num_input_tokens_seen": 0,
  "num_train_epochs": 5,
  "save_steps": 500,
  "total_flos": 355609146412800.0,
  "train_batch_size": 128,
  "trial_name": null,
  "trial_params": null
}
