{
  "best_metric": null,
  "best_model_checkpoint": null,
  "epoch": 5.0,
  "eval_steps": 500,
  "global_step": 255,
  "is_hyper_param_search": false,
  "is_local_process_zero": true,
  "is_world_process_zero": true,
  "log_history": [
    {
      "epoch": 1.0,
      "learning_rate": 0.00022156874493763773,
      "loss": 0.0112,
      "step": 51
    },
    {
      "epoch": 1.0,
      "eval_loss": 1.339392066001892,
      "eval_macro_f1": 0.8029455842037623,
      "eval_runtime": 7.0063,
      "eval_samples_per_second": 139.018,
      "eval_steps_per_second": 2.284,
      "step": 51
    },
    {
      "epoch": 2.0,
      "learning_rate": 0.0001661765587032283,
      "loss": 0.0094,
      "step": 102
    },
    {
      "epoch": 2.0,
      "eval_loss": 1.35654878616333,
      "eval_macro_f1": 0.8053023209905605,
      "eval_runtime": 6.6774,
      "eval_samples_per_second": 145.865,
      "eval_steps_per_second": 2.396,
      "step": 102
    },
    {
      "epoch": 3.0,
      "learning_rate": 0.00011078437246881886,
      "loss": 0.0097,
      "step": 153
    },
    {
      "epoch": 3.0,
      "eval_loss": 1.345324158668518,
      "eval_macro_f1": 0.8131512101200397,
      "eval_runtime": 7.1112,
      "eval_samples_per_second": 136.968,
      "eval_steps_per_second": 2.25,
      "step": 153
    },
    {
      "epoch": 4.0,
      "learning_rate": 5.539218623440943e-05,
      "loss": 0.0027,
      "step": 204
    },
    {
      "epoch": 4.0,
      "eval_loss": 1.3322232961654663,
      "eval_macro_f1": 0.8119739854528625,
      "eval_runtime": 7.0209,
      "eval_samples_per_second": 138.728,
      "eval_steps_per_second": 2.279,
      "step": 204
    },
    {
      "epoch": 5.0,
      "learning_rate": 0.0,
      "loss": 0.0034,
      "step": 255
    },
    {
      "epoch": 5.0,
      "eval_loss": 1.3427211046218872,
      "eval_macro_f1": 0.8137486346021354,
      "eval_runtime": 6.8792,
      "eval_samples_per_second": 141.586,
      "eval_steps_per_second": 2.326,
      "step": 255
    },
    {
      "epoch": 5.0,
      "step": 255,
      "total_flos": 685059978009600.0,
      "train_loss": 0.007284194698520735,
      "train_runtime": 261.7946,
      "train_samples_per_second": 61.479,
      "train_steps_per_second": 0.974
    },
    {
      "epoch": 5.0,
      "eval_loss": 1.3427211046218872,
      "eval_macro_f1": 0.8137486346021354,
      "eval_runtime": 6.8876,
      "eval_samples_per_second": 141.414,
      "eval_steps_per_second": 2.323,
      "step": 255
    }
  ],
  "logging_steps": 500,
  "max_steps": 255,
  "num_input_tokens_seen": 0,
  "num_train_epochs": 5,
  "save_steps": 500,
  "total_flos": 685059978009600.0,
  "train_batch_size": 64,
  "trial_name": null,
  "trial_params": null
}
